llm_wrapper/__init__.py
llm_wrapper/main.py
llm_wrapper-0.1.9.dist-info/LICENSE
llm_wrapper-0.1.9.dist-info/METADATA
llm_wrapper-0.1.9.dist-info/WHEEL
llm_wrapper-0.1.9.dist-info/RECORD
