Metadata-Version: 2.1
Name: llm_wrapper
Version: 0.1.9
Summary: Run llm functions with just inline documentation and no code
Home-page: https://github.com/meirm/llm_functions
Keywords: openai,langchain,pydantic
Author: Meir Michanie
Author-email: meirm@riunx.com
Requires-Python: >=3.11
Classifier: Programming Language :: Python :: 3
Classifier: Programming Language :: Python :: 3.11
Classifier: Programming Language :: Python :: 3.12
Requires-Dist: langchain (>=0.1.0)
Requires-Dist: langchain_community (>=0.0.12)
Requires-Dist: pydantic (>=2.5.3)
